envvalidator.cp313-win_amd64.pyd
envvalidator-1.0.2.dist-info/LICENSE
envvalidator-1.0.2.dist-info/METADATA
envvalidator-1.0.2.dist-info/WHEEL
envvalidator-1.0.2.dist-info/top_level.txt
envvalidator-1.0.2.dist-info/RECORD
