Metadata-Version: 2.2
Name: envvalidator
Version: 1.0.2
Summary: EnvValidator is a lightweight Python library that helps validate environment variables against a predefined schema.
Home-page: https://github.com/Sekiraw/Envvalidator
Author: Qiyaya
Author-email: v2020.bohus.peter@gmail.com
License: Apache-2.0
Keywords: env,validator,validate,environment
Classifier: Development Status :: 4 - Beta
Classifier: Intended Audience :: Developers
Classifier: Topic :: Software Development :: Build Tools
Classifier: License :: OSI Approved :: Apache Software License
Classifier: Programming Language :: Python :: 3.7
Classifier: Programming Language :: Python :: 3.8
Classifier: Programming Language :: Python :: 3.9
Classifier: Programming Language :: Python :: 3.10
Classifier: Programming Language :: Python :: 3.11
Classifier: Programming Language :: Python :: 3.12
Classifier: Programming Language :: Python :: 3.13
License-File: LICENSE
Dynamic: author
Dynamic: author-email
Dynamic: classifier
Dynamic: description
Dynamic: description-content-type
Dynamic: home-page
Dynamic: keywords
Dynamic: license
Dynamic: summary
